simple_cog_client/__init__.py
simple_cog_client/client.py
simple_cog_client/processors.py
simple_cog_client/use_cases.py
simple_cog_client-0.1.2.dist-info/METADATA
simple_cog_client-0.1.2.dist-info/WHEEL
simple_cog_client-0.1.2.dist-info/RECORD
