Metadata-Version: 2.1
Name: simple-cog-client
Version: 0.1.2
Summary: 
Author: Carlos Aranda
Author-email: carlos.aranda@ksms.mx
Requires-Python: >=3.7,<4.0
Classifier: Programming Language :: Python :: 3
Classifier: Programming Language :: Python :: 3.7
Classifier: Programming Language :: Python :: 3.8
Classifier: Programming Language :: Python :: 3.9
Classifier: Programming Language :: Python :: 3.10
Classifier: Programming Language :: Python :: 3.11
Requires-Dist: pillow (>=9.4.0,<10.0.0)
Requires-Dist: requests (>=2.28.2,<3.0.0)
